lotusops/__init__.py
lotusops/_version.py
lotusops/cli/__constants__.py
lotusops/cli/__init__.py
lotusops/cli/lotusops.py
lotusops/cli/lotuspledge.py
lotusops/cli/speedtest.py
lotusops/speedtest/__init__.py
lotusops/speedtest/__precommit1.py
lotusops/speedtest/constants.py
lotusops/speedtest/jsonformat.py
lotusops/speedtest/sectorstatus.py
lotusops/speedtest/textformat.py
lotusops-0.0.1.dist-info/LICENSE-APACHE
lotusops-0.0.1.dist-info/LICENSE-MIT
lotusops-0.0.1.dist-info/METADATA
lotusops-0.0.1.dist-info/WHEEL
lotusops-0.0.1.dist-info/entry_points.txt
lotusops-0.0.1.dist-info/top_level.txt
lotusops-0.0.1.dist-info/RECORD
