Metadata-Version: 1.2
Name: lotusops
Version: 0.0.1
Summary: UNKNOWN
Home-page: https://github.com/deep2essence/lotusops
Author: gaojunying
Author-email: gustav0125@outlook.com
Maintainer: gaojunying
Maintainer-email: gustav0125@outlook.com
License: MIT/Apache-2.0
Platform: UNKNOWN
Classifier: Development Status :: 4 - Beta
Classifier: Intended Audience :: Developers
Classifier: License :: OSI Approved :: MIT License
Classifier: License :: OSI Approved :: Apache Software License
Classifier: Natural Language :: English
Classifier: Operating System :: OS Independent
Classifier: Programming Language :: Python :: 2.7
Classifier: Programming Language :: Python :: 3.5
Classifier: Programming Language :: Python :: 3.6
Classifier: Programming Language :: Python :: Implementation :: CPython
Classifier: Programming Language :: Python :: Implementation :: PyPy
